simpleutils_azan/__init__.py
simpleutils_azan/math_utils.py
simpleutils_azan/setup.py
simpleutils_azan/string_utils.py
simpleutils_azan-0.1.0.dist-info/METADATA
simpleutils_azan-0.1.0.dist-info/WHEEL
simpleutils_azan-0.1.0.dist-info/top_level.txt
simpleutils_azan-0.1.0.dist-info/RECORD
